{
  "Logging": {
    "LogLevel": {
      "Default": "Information",
      "Microsoft.AspNetCore": "Warning"
    }
  },
  "MongoDBSettings": {
    "ConnectionString": "mongodb://postgres:NxPostgrsql@docdb-2024-06-21-01-54-19.cluster-cz0qqo02m0na.eu-west-1.docdb.amazonaws.com:27017/?tls=true&tlsCAFile=/usr/local/share/ca-certificates/global-bundle.pem&replicaSet=rs0&readPreference=secondaryPreferred&retryWrites=false",
    "DatabaseName": "OrderDb"
  },
  "ConnectionStrings": {
    "OrderDbConnection": "Host=orderapi.cz0qqo02m0na.eu-west-1.rds.amazonaws.com;Port=5432;Database=OrderDb;User Id=postgres;Password=NxPostgrsql;"
  },
  "AllowedHosts": "*"
}

